assets/ghost-mcp-demo.gif
src/main.py
src/ghost_mcp/__init__.py
src/ghost_mcp/api.py
src/ghost_mcp/config.py
src/ghost_mcp/exceptions.py
src/ghost_mcp/models.py
src/ghost_mcp/resources.py
src/ghost_mcp/server.py
src/ghost_mcp/tools/__init__.py
src/ghost_mcp/tools/ghost.py
src/ghost_mcp/tools/invites.py
src/ghost_mcp/tools/members.py
src/ghost_mcp/tools/newsletters.py
src/ghost_mcp/tools/offers.py
src/ghost_mcp/tools/posts.py
src/ghost_mcp/tools/roles.py
src/ghost_mcp/tools/tags.py
src/ghost_mcp/tools/tiers.py
src/ghost_mcp/tools/users.py
src/ghost_mcp/tools/webhooks.py
orange_ghost_mcp-0.1.0.dist-info/METADATA
orange_ghost_mcp-0.1.0.dist-info/WHEEL
orange_ghost_mcp-0.1.0.dist-info/licenses/LICENSE
orange_ghost_mcp-0.1.0.dist-info/RECORD
