Metadata-Version: 2.4
Name: orange-ghost-mcp
Version: 0.1.0
Summary: Ghost blog integration MCP server
Author: Fanyang Meng
License-File: LICENSE
Requires-Python: >=3.12
Requires-Dist: httpx
Requires-Dist: mcp[cli]>=1.2.1
Requires-Dist: pyjwt
Requires-Dist: pytz
